desige/__init__.py
desige/core.py
desige/layouts.py
desige/extras/__init__.py
desige/extras/nginx.py
desige/pages/__init__.py
desige/pages/basic_page.py
desige/pages/sitemap.py
desige/pages/validators.py
desige/pages/web_page.py
desige/templates/__init__.py
desige/templates/error_page.py
desige/templates/html_page.py
desige/templates/sitemap.py
desige/templates/web_page.py
desige/templates/extras/__init__.py
desige/templates/extras/nginx.py
desige-0.0.18.dist-info/LICENSE
desige-0.0.18.dist-info/METADATA
desige-0.0.18.dist-info/WHEEL
desige-0.0.18.dist-info/top_level.txt
desige-0.0.18.dist-info/RECORD
