Metadata-Version: 2.1
Name: desige
Version: 0.0.18
Summary: Declassed site generator
Home-page: https://declassed.art/repository/desige
Author: AXY
Author-email: axy@declassed.art
License: UNKNOWN
Platform: UNKNOWN
Classifier: Programming Language :: Python :: 3
Classifier: License :: OSI Approved :: BSD License
Classifier: Operating System :: OS Independent
Classifier: Intended Audience :: Developers
Classifier: Development Status :: 3 - Alpha
Classifier: Topic :: Internet :: WWW/HTTP :: Dynamic Content
Requires-Python: >=3.6
Requires-Dist: axyutils
Requires-Dist: clabate
Requires-Dist: idna
Requires-Dist: python-dateutil
Requires-Dist: pyyaml
